setup.py
rdfspace/__init__.py
rdfspace/space.py
rdfspace.egg-info/PKG-INFO
rdfspace.egg-info/SOURCES.txt
rdfspace.egg-info/dependency_links.txt
rdfspace.egg-info/requires.txt
rdfspace.egg-info/top_level.txt