Metadata-Version: 1.0
Name: rdfspace
Version: 0.0.1
Summary: RDFSpace constructs a vector space 
Home-page: UNKNOWN
Author: Yves Raimond
Author-email: yves.raimond@bbc.co.uk
License: UNKNOWN
Platform: UNKNOWN
